{
	"info": {
		"_postman_id": "1465fe24-e2b0-45b8-a2ec-01a075727f09",
		"name": "Scala",
		"schema": "https://schema.getpostman.com/json/collection/v2.1.0/collection.json",
		"_exporter_id": "24249790"
	},
	"item": [
		{
			"name": "Health check - 200 OK",
			"request": {
				"method": "GET",
				"header": [],
				"url": {
					"raw": "http://localhost:8080/api/healthcheck",
					"protocol": "http",
					"host": [
						"localhost"
					],
					"port": "8080",
					"path": [
						"api",
						"healthcheck"
					]
				}
			},
			"response": []
		},
		{
			"name": "List all products - 200 OK",
			"request": {
				"method": "GET",
				"header": [],
				"url": {
					"raw": "http://localhost:8080/api/v1/product",
					"protocol": "http",
					"host": [
						"localhost"
					],
					"port": "8080",
					"path": [
						"api",
						"v1",
						"product"
					]
				}
			},
			"response": []
		},
		{
			"name": "Create product - 200 OK",
			"request": {
				"method": "POST",
				"header": [],
				"body": {
					"mode": "raw",
					"raw": "{\r\n    \"name\": \"test\",\r\n    \"calories\": 1\r\n}",
					"options": {
						"raw": {
							"language": "json"
						}
					}
				},
				"url": {
					"raw": "http://localhost:8080/api/v1/product",
					"protocol": "http",
					"host": [
						"localhost"
					],
					"port": "8080",
					"path": [
						"api",
						"v1",
						"product"
					]
				}
			},
			"response": []
		}
	]
}